odoo10_addon_l10n_ch_hr_payroll_report-10.0.1.0.0.99.dev14-py3.8-nspkg.pth
odoo/addons/l10n_ch_hr_payroll_report/README.rst
odoo/addons/l10n_ch_hr_payroll_report/__init__.py
odoo/addons/l10n_ch_hr_payroll_report/__manifest__.py
odoo/addons/l10n_ch_hr_payroll_report/data/hr.salary.rule.xml
odoo/addons/l10n_ch_hr_payroll_report/i18n/am.po
odoo/addons/l10n_ch_hr_payroll_report/i18n/ar.po
odoo/addons/l10n_ch_hr_payroll_report/i18n/bg.po
odoo/addons/l10n_ch_hr_payroll_report/i18n/bs.po
odoo/addons/l10n_ch_hr_payroll_report/i18n/ca.po
odoo/addons/l10n_ch_hr_payroll_report/i18n/cs.po
odoo/addons/l10n_ch_hr_payroll_report/i18n/da.po
odoo/addons/l10n_ch_hr_payroll_report/i18n/de.po
odoo/addons/l10n_ch_hr_payroll_report/i18n/el_GR.po
odoo/addons/l10n_ch_hr_payroll_report/i18n/en_GB.po
odoo/addons/l10n_ch_hr_payroll_report/i18n/es.po
odoo/addons/l10n_ch_hr_payroll_report/i18n/es_AR.po
odoo/addons/l10n_ch_hr_payroll_report/i18n/es_CO.po
odoo/addons/l10n_ch_hr_payroll_report/i18n/es_CR.po
odoo/addons/l10n_ch_hr_payroll_report/i18n/es_DO.po
odoo/addons/l10n_ch_hr_payroll_report/i18n/es_EC.po
odoo/addons/l10n_ch_hr_payroll_report/i18n/es_ES.po
odoo/addons/l10n_ch_hr_payroll_report/i18n/es_MX.po
odoo/addons/l10n_ch_hr_payroll_report/i18n/es_PE.po
odoo/addons/l10n_ch_hr_payroll_report/i18n/es_VE.po
odoo/addons/l10n_ch_hr_payroll_report/i18n/et.po
odoo/addons/l10n_ch_hr_payroll_report/i18n/eu.po
odoo/addons/l10n_ch_hr_payroll_report/i18n/fa.po
odoo/addons/l10n_ch_hr_payroll_report/i18n/fi.po
odoo/addons/l10n_ch_hr_payroll_report/i18n/fr.po
odoo/addons/l10n_ch_hr_payroll_report/i18n/fr_CH.po
odoo/addons/l10n_ch_hr_payroll_report/i18n/gl.po
odoo/addons/l10n_ch_hr_payroll_report/i18n/gl_ES.po
odoo/addons/l10n_ch_hr_payroll_report/i18n/he.po
odoo/addons/l10n_ch_hr_payroll_report/i18n/hr.po
odoo/addons/l10n_ch_hr_payroll_report/i18n/hr_HR.po
odoo/addons/l10n_ch_hr_payroll_report/i18n/hu.po
odoo/addons/l10n_ch_hr_payroll_report/i18n/id.po
odoo/addons/l10n_ch_hr_payroll_report/i18n/it.po
odoo10_addon_l10n_ch_hr_payroll_report-10.0.1.0.0.99.dev14.dist-info/METADATA
odoo10_addon_l10n_ch_hr_payroll_report-10.0.1.0.0.99.dev14.dist-info/WHEEL
odoo10_addon_l10n_ch_hr_payroll_report-10.0.1.0.0.99.dev14.dist-info/namespace_packages.txt
odoo10_addon_l10n_ch_hr_payroll_report-10.0.1.0.0.99.dev14.dist-info/top_level.txt
odoo10_addon_l10n_ch_hr_payroll_report-10.0.1.0.0.99.dev14.dist-info/RECORD
